datasling/app/__init__.py
datasling/app/main.py
datasling/app/modules/__init__.py
datasling/app/modules/config.py
datasling/app/modules/db.py
datasling/app/modules/df_utils.py
datasling/app/modules/file_utils.py
datasling/app/modules/history_manager.py
datasling/app/modules/info.py
datasling/app/modules/query_processor.py
datasling/app/modules/ui.py
datasling-0.0.23.dist-info/licenses/LICENSE
datasling-0.0.23.dist-info/METADATA
datasling-0.0.23.dist-info/WHEEL
datasling-0.0.23.dist-info/entry_points.txt
datasling-0.0.23.dist-info/top_level.txt
datasling-0.0.23.dist-info/RECORD
